{"v":"5.9.0","fr":60,"ip":0,"op":180,"w":500,"h":500,"nm":"07 Lotus","ddd":0,"assets":[],"layers":[{"ddd":0,"ind":1,"ty":1,"nm":"Main Stroke width - Color Ctrl","sr":1,"ks":{"o":{"a":0,"k":0,"ix":11},"r":{"a":0,"k":0,"ix":10},"p":{"a":0,"k":[250,250,0],"ix":2,"l":2},"a":{"a":0,"k":[50,50,0],"ix":1,"l":2},"s":{"a":0,"k":[100,100,100],"ix":6,"l":2}},"ao":0,"ef":[{"ty":5,"nm":"Stroke width","np":3,"mn":"ADBE Slider Control","ix":1,"en":1,"ef":[{"ty":0,"nm":"Slider","mn":"ADBE Slider Control-0001","ix":1,"v":{"a":0,"k":16,"ix":1}}]},{"ty":5,"nm":"Base Color","np":3,"mn":"ADBE Color Control","ix":2,"en":1,"ef":[{"ty":2,"nm":"Color","mn":"ADBE Color Control-0001","ix":1,"v":{"a":0,"k":[0.019607843831,0.164705887437,0.458823531866,1],"ix":1,"x":"var $bm_rt;\n$bm_rt = effect('Base Color')('Color');"}}]},{"ty":5,"nm":"Highlight","np":3,"mn":"ADBE Color Control","ix":3,"en":1,"ef":[{"ty":2,"nm":"Color","mn":"ADBE Color Control-0001","ix":1,"v":{"a":0,"k":[0.992156863213,0.796078443527,0.313725501299,1],"ix":1}}]},{"ty":5,"nm":"Stroke width 2","np":3,"mn":"ADBE Slider Control","ix":4,"en":1,"ef":[{"ty":0,"nm":"Slider","mn":"ADBE Slider Control-0001","ix":1,"v":{"a":0,"k":18,"ix":1}}]}],"sw":100,"sh":100,"sc":"#ffffff","ip":0,"op":185,"st":0,"bm":0},{"ddd":0,"ind":2,"ty":4,"nm":"circles","sr":1,"ks":{"o":{"a":0,"k":100,"ix":11},"r":{"a":0,"k":0,"ix":10},"p":{"a":0,"k":[265.014,138.437,0],"ix":2,"l":2},"a":{"a":0,"k":[265.014,138.437,0],"ix":1,"l":2},"s":{"a":0,"k":[100,100,100],"ix":6,"l":2}},"ao":0,"shapes":[{"ty":"gr","it":[{"ty":"gr","it":[{"ind":0,"ty":"sh","ix":1,"ks":{"a":1,"k":[{"i":{"x":0.667,"y":1},"o":{"x":0.333,"y":0},"t":23,"s":[{"i":[[-8.71,0],[0,8.71],[8.71,0],[0,-8.71]],"o":[[8.71,0],[0,-8.71],[-8.71,0],[0,8.71]],"v":[[387.311,199.074],[403.125,183.259],[387.311,167.445],[371.497,183.259]],"c":true}]},{"i":{"x":0.667,"y":1},"o":{"x":0.333,"y":0},"t":98,"s":[{"i":[[-8.71,0],[0,8.71],[8.71,0],[0,-8.71]],"o":[[8.71,0],[0,-8.71],[-8.71,0],[0,8.71]],"v":[[405.263,161.887],[421.077,146.073],[405.263,130.258],[389.449,146.073]],"c":true}]},{"t":164,"s":[{"i":[[-8.71,0],[0,8.71],[8.71,0],[0,-8.71]],"o":[[8.71,0],[0,-8.71],[-8.71,0],[0,8.71]],"v":[[387.311,199.074],[403.125,183.259],[387.311,167.445],[371.497,183.259]],"c":true}]}],"ix":2},"nm":"Path 1","mn":"ADBE Vector Shape - Group","hd":false},{"ind":1,"ty":"sh","ix":2,"ks":{"a":1,"k":[{"i":{"x":0.667,"y":1},"o":{"x":0.333,"y":0},"t":16,"s":[{"i":[[-8.71,0],[0,8.71],[8.71,0],[0,-8.71]],"o":[[8.71,0],[0,-8.71],[-8.71,0],[0,8.71]],"v":[[142.717,172.717],[158.531,156.902],[142.717,141.088],[126.902,156.902]],"c":true}]},{"i":{"x":0.667,"y":1},"o":{"x":0.333,"y":0},"t":91,"s":[{"i":[[-8.71,0],[0,8.71],[8.71,0],[0,-8.71]],"o":[[8.71,0],[0,-8.71],[-8.71,0],[0,8.71]],"v":[[127.757,129.973],[143.571,114.159],[127.757,98.345],[111.942,114.159]],"c":true}]},{"t":157,"s":[{"i":[[-8.71,0],[0,8.71],[8.71,0],[0,-8.71]],"o":[[8.71,0],[0,-8.71],[-8.71,0],[0,8.71]],"v":[[142.717,172.717],[158.531,156.902],[142.717,141.088],[126.902,156.902]],"c":true}]}],"ix":2},"nm":"Path 2","mn":"ADBE Vector Shape - Group","hd":false},{"ind":2,"ty":"sh","ix":3,"ks":{"a":1,"k":[{"i":{"x":0.667,"y":1},"o":{"x":0.333,"y":0},"t":9,"s":[{"i":[[-8.71,0],[0,8.71],[8.71,0],[0,-8.71]],"o":[[8.71,0],[0,-8.71],[-8.71,0],[0,8.71]],"v":[[305.428,109.428],[321.243,93.614],[305.428,77.8],[289.614,93.614]],"c":true}]},{"i":{"x":0.667,"y":1},"o":{"x":0.333,"y":0},"t":84,"s":[{"i":[[-8.71,0],[0,8.71],[8.71,0],[0,-8.71]],"o":[[8.71,0],[0,-8.71],[-8.71,0],[0,8.71]],"v":[[310.13,79.081],[325.945,63.266],[310.13,47.452],[294.316,63.266]],"c":true}]},{"t":150,"s":[{"i":[[-8.71,0],[0,8.71],[8.71,0],[0,-8.71]],"o":[[8.71,0],[0,-8.71],[-8.71,0],[0,8.71]],"v":[[305.428,109.428],[321.243,93.614],[305.428,77.8],[289.614,93.614]],"c":true}]}],"ix":2},"nm":"Path 3","mn":"ADBE Vector Shape - Group","hd":false},{"ty":"tr","p":{"a":0,"k":[-136.5,-57.5],"ix":2},"a":{"a":0,"k":[265.014,138.437],"ix":1},"s":{"a":1,"k":[{"i":{"x":[0.667,0.667],"y":[1,1]},"o":{"x":[0.333,0.333],"y":[0,0]},"t":15,"s":[100,100]},{"i":{"x":[0.667,0.667],"y":[1,1]},"o":{"x":[0.333,0.333],"y":[0,0]},"t":54,"s":[117,117]},{"i":{"x":[0.667,0.667],"y":[1,1]},"o":{"x":[0.333,0.333],"y":[0,0]},"t":107,"s":[95,95]},{"t":164,"s":[100,100]}],"ix":3},"r":{"a":0,"k":0,"ix":6},"o":{"a":0,"k":100,"ix":7},"sk":{"a":0,"k":0,"ix":4},"sa":{"a":0,"k":0,"ix":5},"nm":"Transform"}],"nm":"Group 1","np":3,"cix":2,"bm":0,"ix":1,"mn":"ADBE Vector Group","hd":false},{"ty":"st","c":{"a":0,"k":[0.992156863213,0.796078443527,0.313725501299,1],"ix":3,"x":"var $bm_rt;\n$bm_rt = thisComp.layer('Main Stroke width - Color Ctrl').effect('Highlight')('Color');"},"o":{"a":0,"k":100,"ix":4},"w":{"a":0,"k":16,"ix":5,"x":"var $bm_rt;\n$bm_rt = thisComp.layer('Main Stroke width - Color Ctrl').effect('Stroke width')('Slider');"},"lc":2,"lj":2,"bm":0,"nm":"Stroke 1","mn":"ADBE Vector Graphic - Stroke","hd":false},{"ty":"tr","p":{"a":0,"k":[387.311,183.259],"ix":2},"a":{"a":0,"k":[0,0],"ix":1},"s":{"a":0,"k":[100,100],"ix":3},"r":{"a":0,"k":0,"ix":6},"o":{"a":0,"k":100,"ix":7},"sk":{"a":0,"k":0,"ix":4},"sa":{"a":0,"k":0,"ix":5},"nm":"Transform"}],"nm":"Group 1","np":2,"cix":2,"bm":0,"ix":1,"mn":"ADBE Vector Group","hd":false}],"ip":0,"op":180,"st":0,"bm":0},{"ddd":0,"ind":3,"ty":4,"nm":"Petal 03","sr":1,"ks":{"o":{"a":0,"k":100,"ix":11},"r":{"a":0,"k":0,"ix":10},"p":{"a":0,"k":[250,282.627,0],"ix":2,"l":2},"a":{"a":0,"k":[0,0,0],"ix":1,"l":2},"s":{"a":0,"k":[100,100,100],"ix":6,"l":2}},"ao":0,"shapes":[{"ty":"gr","it":[{"ty":"gr","it":[{"ind":0,"ty":"sh","ix":1,"ks":{"a":1,"k":[{"i":{"x":0.598,"y":1},"o":{"x":0.434,"y":0},"t":15,"s":[{"i":[[0,0],[0,0],[-115.556,0],[0,50.9],[7.614,-88.055]],"o":[[-6.749,-89.671],[0,50.9],[115.556,0],[0,0],[0,0]],"v":[[-77.751,55.044],[-171.5,-23.386],[0,62.822],[171.5,-23.386],[78.511,55.803]],"c":false}]},{"i":{"x":0.833,"y":1},"o":{"x":0.416,"y":0},"t":81,"s":[{"i":[[0,0],[0,0],[-115.556,0],[0,50.9],[7.812,-86.259]],"o":[[-7.423,-88.698],[0,50.9],[115.556,0],[0,0],[0,0]],"v":[[-78.403,56.606],[-185.786,-17.36],[0,62.822],[179.758,-14.904],[79.417,57.718]],"c":false}]},{"t":153,"s":[{"i":[[0,0],[0,0],[-115.556,0],[0,50.9],[7.614,-88.055]],"o":[[-6.749,-89.671],[0,50.9],[115.556,0],[0,0],[0,0]],"v":[[-77.751,55.044],[-171.5,-23.386],[0,62.822],[171.5,-23.386],[78.511,55.803]],"c":false}]}],"ix":2},"nm":"Path 1","mn":"ADBE Vector Shape - Group","hd":false},{"ty":"tr","p":{"a":0,"k":[0,67],"ix":2},"a":{"a":0,"k":[0,63],"ix":1},"s":{"a":1,"k":[{"i":{"x":[0.598,0.598],"y":[1,1]},"o":{"x":[0.434,0.434],"y":[0,0]},"t":15,"s":[100,100]},{"i":{"x":[0.61,0.61],"y":[1,1]},"o":{"x":[0.416,0.416],"y":[0,0]},"t":81,"s":[112,112]},{"t":153,"s":[100,100]}],"ix":3},"r":{"a":0,"k":0,"ix":6},"o":{"a":0,"k":100,"ix":7},"sk":{"a":0,"k":0,"ix":4},"sa":{"a":0,"k":0,"ix":5},"nm":"Transform"}],"nm":"Group 1","np":2,"cix":2,"bm":0,"ix":1,"mn":"ADBE Vector Group","hd":false},{"ty":"st","c":{"a":0,"k":[0,0,0,1],"ix":3,"x":"var $bm_rt;\n$bm_rt = thisComp.layer('Main Stroke width - Color Ctrl').effect('Base Color')('Color');"},"o":{"a":0,"k":100,"ix":4},"w":{"a":0,"k":16,"ix":5,"x":"var $bm_rt;\n$bm_rt = thisComp.layer('Main Stroke width - Color Ctrl').effect('Stroke width')('Slider');"},"lc":2,"lj":2,"bm":0,"nm":"Stroke 1","mn":"ADBE Vector Graphic - Stroke","hd":false},{"ty":"fl","c":{"a":0,"k":[0.737254901961,0.603921568627,0.956862745098,1],"ix":4},"o":{"a":0,"k":100,"ix":5},"r":1,"bm":0,"nm":"Fill 1","mn":"ADBE Vector Graphic - Fill","hd":false},{"ty":"tr","p":{"a":0,"k":[0,0],"ix":2},"a":{"a":0,"k":[0,0],"ix":1},"s":{"a":0,"k":[100,100],"ix":3},"r":{"a":0,"k":0,"ix":6},"o":{"a":0,"k":100,"ix":7},"sk":{"a":0,"k":0,"ix":4},"sa":{"a":0,"k":0,"ix":5},"nm":"Transform"}],"nm":"Petal 04","np":3,"cix":2,"bm":0,"ix":1,"mn":"ADBE Vector Group","hd":false},{"ty":"gr","it":[{"ind":0,"ty":"sh","ix":1,"ks":{"a":1,"k":[{"i":{"x":0.597,"y":1},"o":{"x":0.436,"y":0},"t":14,"s":[{"i":[[0,0],[0,0]],"o":[[0,0],[0,0]],"v":[[0,26.513],[0,-26.513]],"c":false}]},{"i":{"x":0.61,"y":1},"o":{"x":0.416,"y":0},"t":80,"s":[{"i":[[0,0],[0,0]],"o":[[0,0],[0,0]],"v":[[0,26.513],[0,-37.513]],"c":false}]},{"t":153,"s":[{"i":[[0,0],[0,0]],"o":[[0,0],[0,0]],"v":[[0,26.513],[0,-26.513]],"c":false}]}],"ix":2},"nm":"Path 1","mn":"ADBE Vector Shape - Group","hd":false},{"ty":"st","c":{"a":0,"k":[0.407843142748,0.392156869173,0.96862745285,1],"ix":3},"o":{"a":0,"k":100,"ix":4},"w":{"a":0,"k":16,"ix":5,"x":"var $bm_rt;\n$bm_rt = thisComp.layer('Main Stroke width - Color Ctrl').effect('Stroke width')('Slider');"},"lc":2,"lj":2,"bm":0,"nm":"Stroke 1","mn":"ADBE Vector Graphic - Stroke","hd":false},{"ty":"tr","p":{"a":0,"k":[0,29],"ix":2},"a":{"a":0,"k":[0,0],"ix":1},"s":{"a":0,"k":[100,100],"ix":3},"r":{"a":0,"k":0,"ix":6},"o":{"a":0,"k":100,"ix":7},"sk":{"a":0,"k":0,"ix":4},"sa":{"a":0,"k":0,"ix":5},"nm":"Transform"}],"nm":"Petal 03 Line","np":2,"cix":2,"bm":0,"ix":2,"mn":"ADBE Vector Group","hd":false},{"ty":"gr","it":[{"ty":"gr","it":[{"ind":1,"ty":"sh","ix":2,"ks":{"a":1,"k":[{"i":{"x":0.598,"y":1},"o":{"x":0.434,"y":0},"t":15,"s":[{"i":[[0,0],[-35.113,17.559],[46.691,-37.876]],"o":[[-46.569,-37.889],[35.133,17.569],[0,0]],"v":[[-24.627,61.02],[0,-62.822],[24.547,61.085]],"c":false}]},{"i":{"x":0.61,"y":1},"o":{"x":0.416,"y":0},"t":81,"s":[{"i":[[0,0],[-35.113,17.559],[56.927,-32.574]],"o":[[-53.051,-38.536],[35.133,17.569],[0,0]],"v":[[-24.627,61.02],[1.339,-68.849],[24.547,61.085]],"c":false}]},{"t":153,"s":[{"i":[[0,0],[-35.113,17.559],[46.691,-37.876]],"o":[[-46.569,-37.889],[35.133,17.569],[0,0]],"v":[[-24.627,61.02],[0,-62.822],[24.547,61.085]],"c":false}]}],"ix":2},"nm":"Path 2","mn":"ADBE Vector Shape - Group","hd":false},{"ty":"tr","p":{"a":0,"k":[0,67],"ix":2},"a":{"a":0,"k":[0,63],"ix":1},"s":{"a":1,"k":[{"i":{"x":[0.598,0.598],"y":[1,1]},"o":{"x":[0.434,0.434],"y":[0,0]},"t":15,"s":[100,100]},{"i":{"x":[0.61,0.61],"y":[1,1]},"o":{"x":[0.416,0.416],"y":[0,0]},"t":81,"s":[112,112]},{"t":153,"s":[100,100]}],"ix":3},"r":{"a":0,"k":0,"ix":6},"o":{"a":0,"k":100,"ix":7},"sk":{"a":0,"k":0,"ix":4},"sa":{"a":0,"k":0,"ix":5},"nm":"Transform"}],"nm":"Group 1","np":2,"cix":2,"bm":0,"ix":1,"mn":"ADBE Vector Group","hd":false},{"ty":"st","c":{"a":0,"k":[0,0,0,1],"ix":3,"x":"var $bm_rt;\n$bm_rt = thisComp.layer('Main Stroke width - Color Ctrl').effect('Base Color')('Color');"},"o":{"a":0,"k":100,"ix":4},"w":{"a":0,"k":16,"ix":5,"x":"var $bm_rt;\n$bm_rt = thisComp.layer('Main Stroke width - Color Ctrl').effect('Stroke width')('Slider');"},"lc":2,"lj":2,"bm":0,"nm":"Stroke 1","mn":"ADBE Vector Graphic - Stroke","hd":false},{"ty":"fl","c":{"a":0,"k":[0.737254917622,0.603921592236,0.956862747669,1],"ix":4},"o":{"a":0,"k":100,"ix":5},"r":1,"bm":0,"nm":"Fill 1","mn":"ADBE Vector Graphic - Fill","hd":false},{"ty":"tr","p":{"a":0,"k":[0,0],"ix":2},"a":{"a":0,"k":[0,0],"ix":1},"s":{"a":0,"k":[100,100],"ix":3},"r":{"a":0,"k":0,"ix":6},"o":{"a":0,"k":100,"ix":7},"sk":{"a":0,"k":0,"ix":4},"sa":{"a":0,"k":0,"ix":5},"nm":"Transform"}],"nm":"Petal 03","np":3,"cix":2,"bm":0,"ix":3,"mn":"ADBE Vector Group","hd":false}],"ip":0,"op":180,"st":0,"bm":0},{"ddd":0,"ind":4,"ty":4,"nm":"Petal 02","sr":1,"ks":{"o":{"a":0,"k":100,"ix":11},"r":{"a":0,"k":0,"ix":10},"p":{"a":0,"k":[252.071,279.711,0],"ix":2,"l":2},"a":{"a":0,"k":[0,0,0],"ix":1,"l":2},"s":{"a":0,"k":[100,100,100],"ix":6,"l":2}},"ao":0,"shapes":[{"ty":"gr","it":[{"ind":0,"ty":"sh","ix":1,"ks":{"a":0,"k":{"i":[[32.5,6.875],[0,0],[0,0],[-45.625,5.375],[0,0]],"o":[[-32.5,-6.875],[0,0],[0,0],[45.625,-5.375],[0,0]],"v":[[64.304,14.664],[-120.071,25.789],[-94.696,59.539],[7.303,71.289],[120.804,49.289]],"c":true},"ix":2},"nm":"Path 1","mn":"ADBE Vector Shape - Group","hd":false},{"ty":"fl","c":{"a":0,"k":[0.407843167174,0.392156892664,0.968627510819,1],"ix":4},"o":{"a":0,"k":100,"ix":5},"r":1,"bm":0,"nm":"Fill 1","mn":"ADBE Vector Graphic - Fill","hd":false},{"ty":"tr","p":{"a":0,"k":[0,0],"ix":2},"a":{"a":0,"k":[0,0],"ix":1},"s":{"a":0,"k":[100,100],"ix":3},"r":{"a":0,"k":0,"ix":6},"o":{"a":0,"k":100,"ix":7},"sk":{"a":0,"k":0,"ix":4},"sa":{"a":0,"k":0,"ix":5},"nm":"Transform"}],"nm":"Shape 1","np":3,"cix":2,"bm":0,"ix":1,"mn":"ADBE Vector Group","hd":false},{"ty":"gr","it":[{"ty":"gr","it":[{"ind":0,"ty":"sh","ix":1,"ks":{"a":0,"k":{"i":[[0,0],[0.175,0.323],[12.733,2.59],[1.668,-22.594],[0.01,-0.143]],"o":[[-0.165,-0.325],[-10.168,-18.829],[-13.77,10.491],[-0.011,0.143],[0,0]],"v":[[-2.571,69.539],[-39.746,-25.711],[-88.082,-62.289],[-113.929,-10.711],[-107.571,54.539]],"c":false},"ix":2},"nm":"Path 1","mn":"ADBE Vector Shape - Group","hd":false},{"ind":1,"ty":"sh","ix":2,"ks":{"a":0,"k":{"i":[[-0.221,0.444],[-0.238,0.44],[-12.734,2.59],[-1.668,-22.594],[-0.015,-0.223]],"o":[[0.221,-0.444],[10.168,-18.829],[13.77,10.491],[0.016,0.222],[0,0]],"v":[[-3.946,67.789],[35.602,-25.711],[83.938,-62.289],[109.785,-10.711],[114.429,48.289]],"c":false},"ix":2},"nm":"Path 2","mn":"ADBE Vector Shape - Group","hd":false},{"ty":"tr","p":{"a":0,"k":[0,63],"ix":2},"a":{"a":0,"k":[0,63],"ix":1},"s":{"a":1,"k":[{"i":{"x":[0.598,0.598],"y":[1,1]},"o":{"x":[0.434,0.434],"y":[0,0]},"t":15,"s":[100,100]},{"i":{"x":[0.61,0.61],"y":[1,1]},"o":{"x":[0.416,0.416],"y":[0,0]},"t":81,"s":[108,108]},{"t":153,"s":[100,100]}],"ix":3},"r":{"a":0,"k":0,"ix":6},"o":{"a":0,"k":100,"ix":7},"sk":{"a":0,"k":0,"ix":4},"sa":{"a":0,"k":0,"ix":5},"nm":"Transform"}],"nm":"Group 1","np":2,"cix":2,"bm":0,"ix":1,"mn":"ADBE Vector Group","hd":false},{"ty":"st","c":{"a":0,"k":[0,0,0,1],"ix":3,"x":"var $bm_rt;\n$bm_rt = thisComp.layer('Main Stroke width - Color Ctrl').effect('Base Color')('Color');"},"o":{"a":0,"k":100,"ix":4},"w":{"a":0,"k":16,"ix":5,"x":"var $bm_rt;\n$bm_rt = thisComp.layer('Main Stroke width - Color Ctrl').effect('Stroke width')('Slider');"},"lc":2,"lj":2,"bm":0,"nm":"Stroke 1","mn":"ADBE Vector Graphic - Stroke","hd":false},{"ty":"fl","c":{"a":0,"k":[0.407843167174,0.392156892664,0.968627510819,1],"ix":4},"o":{"a":0,"k":100,"ix":5},"r":1,"bm":0,"nm":"Fill 1","mn":"ADBE Vector Graphic - Fill","hd":false},{"ty":"tr","p":{"a":0,"k":[0,0],"ix":2},"a":{"a":0,"k":[0,0],"ix":1},"s":{"a":0,"k":[100,100],"ix":3},"r":{"a":0,"k":0,"ix":6},"o":{"a":0,"k":100,"ix":7},"sk":{"a":0,"k":0,"ix":4},"sa":{"a":0,"k":0,"ix":5},"nm":"Transform"}],"nm":"Petal 02","np":3,"cix":2,"bm":0,"ix":2,"mn":"ADBE Vector Group","hd":false}],"ip":0,"op":180,"st":0,"bm":0},{"ddd":0,"ind":5,"ty":4,"nm":"polen","sr":1,"ks":{"o":{"a":0,"k":100,"ix":11},"r":{"a":0,"k":0,"ix":10},"p":{"a":0,"k":[251.728,268.627,0],"ix":2,"l":2},"a":{"a":0,"k":[0,0,0],"ix":1,"l":2},"s":{"a":0,"k":[100,100,100],"ix":6,"l":2}},"ao":0,"shapes":[{"ty":"gr","it":[{"ty":"rc","d":1,"s":{"a":0,"k":[370,332],"ix":2},"p":{"a":0,"k":[0,0],"ix":3},"r":{"a":0,"k":0,"ix":4},"nm":"Rectangle Path 1","mn":"ADBE Vector Shape - Rect","hd":false},{"ty":"fl","c":{"a":0,"k":[0.992156922583,0.560784313725,0.003921568627,1],"ix":4},"o":{"a":0,"k":100,"ix":5},"r":1,"bm":0,"nm":"Fill 1","mn":"ADBE Vector Graphic - Fill","hd":false},{"ty":"tr","p":{"a":0,"k":[-10.728,-94.627],"ix":2},"a":{"a":0,"k":[0,0],"ix":1},"s":{"a":0,"k":[100,100],"ix":3},"r":{"a":0,"k":0,"ix":6},"o":{"a":0,"k":0,"ix":7},"sk":{"a":0,"k":0,"ix":4},"sa":{"a":0,"k":0,"ix":5},"nm":"Transform"}],"nm":"Rectangle 1","np":3,"cix":2,"bm":0,"ix":1,"mn":"ADBE Vector Group","hd":false},{"ty":"gr","it":[{"ind":0,"ty":"sh","ix":1,"ks":{"a":1,"k":[{"i":{"x":0.667,"y":1},"o":{"x":0.167,"y":0},"t":40,"s":[{"i":[[0,0],[0,0]],"o":[[0,0],[0,0]],"v":[[86.397,-45.85],[86.403,-45.85]],"c":false}]},{"t":152,"s":[{"i":[[0,0],[0,0]],"o":[[0,0],[0,0]],"v":[[121.897,-215.35],[121.903,-215.35]],"c":false}]}],"ix":2},"nm":"Path 1","mn":"ADBE Vector Shape - Group","hd":false},{"ind":1,"ty":"sh","ix":2,"ks":{"a":1,"k":[{"i":{"x":0.667,"y":1},"o":{"x":0.333,"y":0},"t":32,"s":[{"i":[[0,0],[0,0]],"o":[[0,0],[0,0]],"v":[[24.047,-23.25],[24.053,-23.25]],"c":false}]},{"t":146,"s":[{"i":[[0,0],[0,0]],"o":[[0,0],[0,0]],"v":[[64.547,-175.25],[64.553,-175.25]],"c":false}]}],"ix":2},"nm":"Path 2","mn":"ADBE Vector Shape - Group","hd":false},{"ind":2,"ty":"sh","ix":3,"ks":{"a":1,"k":[{"i":{"x":0.667,"y":1},"o":{"x":0.333,"y":0},"t":43,"s":[{"i":[[0,0],[0,0]],"o":[[0,0],[0,0]],"v":[[-15.153,-36.15],[-15.147,-36.15]],"c":false}]},{"t":139,"s":[{"i":[[0,0],[0,0]],"o":[[0,0],[0,0]],"v":[[-16.653,-201.15],[-16.647,-201.15]],"c":false}]}],"ix":2},"nm":"Path 3","mn":"ADBE Vector Shape - Group","hd":false},{"ind":3,"ty":"sh","ix":4,"ks":{"a":1,"k":[{"i":{"x":0.667,"y":1},"o":{"x":0.333,"y":0},"t":37,"s":[{"i":[[0,0],[0,0]],"o":[[0,0],[0,0]],"v":[[-102.903,-33.6],[-102.897,-33.6]],"c":false}]},{"t":149,"s":[{"i":[[0,0],[0,0]],"o":[[0,0],[0,0]],"v":[[-138.903,-175.1],[-138.897,-175.1]],"c":false}]}],"ix":2},"nm":"Path 4","mn":"ADBE Vector Shape - Group","hd":false},{"ind":4,"ty":"sh","ix":5,"ks":{"a":1,"k":[{"i":{"x":0.667,"y":1},"o":{"x":0.333,"y":0},"t":32,"s":[{"i":[[0,0],[0,0]],"o":[[0,0],[0,0]],"v":[[-81.153,-33.75],[-81.148,-33.75]],"c":false}]},{"t":133,"s":[{"i":[[0,0],[0,0]],"o":[[0,0],[0,0]],"v":[[-67.903,-231.25],[-67.898,-231.25]],"c":false}]}],"ix":2},"nm":"Path 5","mn":"ADBE Vector Shape - Group","hd":false},{"ty":"st","c":{"a":0,"k":[0,0,0,1],"ix":3,"x":"var $bm_rt;\n$bm_rt = thisComp.layer('Main Stroke width - Color Ctrl').effect('Highlight')('Color');"},"o":{"a":0,"k":100,"ix":4},"w":{"a":0,"k":16,"ix":5,"x":"var $bm_rt;\n$bm_rt = thisComp.layer('Main Stroke width - Color Ctrl').effect('Stroke width')('Slider');"},"lc":2,"lj":2,"bm":0,"nm":"Stroke 1","mn":"ADBE Vector Graphic - Stroke","hd":false},{"ty":"tr","p":{"a":0,"k":[0,0],"ix":2},"a":{"a":0,"k":[0,0],"ix":1},"s":{"a":0,"k":[100,100],"ix":3},"r":{"a":0,"k":0,"ix":6},"o":{"a":1,"k":[{"i":{"x":[0.667],"y":[1]},"o":{"x":[0.333],"y":[0]},"t":141,"s":[100]},{"t":150,"s":[0]}],"ix":7},"sk":{"a":0,"k":0,"ix":4},"sa":{"a":0,"k":0,"ix":5},"nm":"Transform"}],"nm":"space","np":6,"cix":2,"bm":0,"ix":2,"mn":"ADBE Vector Group","hd":false}],"ip":0,"op":180,"st":0,"bm":0},{"ddd":0,"ind":6,"ty":4,"nm":"Petal 01","sr":1,"ks":{"o":{"a":0,"k":100,"ix":11},"r":{"a":0,"k":0,"ix":10},"p":{"a":0,"k":[250.049,175.322,0],"ix":2,"l":2},"a":{"a":0,"k":[0,0,0],"ix":1,"l":2},"s":{"a":0,"k":[100,100,100],"ix":6,"l":2}},"ao":0,"shapes":[{"ty":"gr","it":[{"ty":"gr","it":[{"ind":0,"ty":"sh","ix":1,"ks":{"a":1,"k":[{"i":{"x":0.598,"y":1},"o":{"x":0.434,"y":0},"t":15,"s":[{"i":[[0,0],[28.842,14.423],[9.556,-39.913]],"o":[[-9.452,-40.071],[-28.743,14.374],[0,0]],"v":[[67.52,46.796],[-0.049,-44.796],[-67.52,46.382]],"c":false}]},{"i":{"x":0.61,"y":1},"o":{"x":0.416,"y":0},"t":81,"s":[{"i":[[0,0],[28.842,14.423],[9.556,-39.913]],"o":[[-9.452,-40.071],[-28.743,14.374],[0,0]],"v":[[62.779,32.572],[-0.049,-44.796],[-63.856,33.02]],"c":false}]},{"t":153,"s":[{"i":[[0,0],[28.842,14.423],[9.556,-39.913]],"o":[[-9.452,-40.071],[-28.743,14.374],[0,0]],"v":[[67.52,46.796],[-0.049,-44.796],[-67.52,46.382]],"c":false}]}],"ix":2},"nm":"Path 1","mn":"ADBE Vector Shape - Group","hd":false},{"ty":"tr","p":{"a":0,"k":[0,1],"ix":2},"a":{"a":0,"k":[0,1],"ix":1},"s":{"a":1,"k":[{"i":{"x":[0.598,0.598],"y":[1,1]},"o":{"x":[0.434,0.434],"y":[0,0]},"t":15,"s":[100,100]},{"i":{"x":[0.61,0.61],"y":[1,1]},"o":{"x":[0.416,0.416],"y":[0,0]},"t":81,"s":[116,116]},{"t":153,"s":[100,100]}],"ix":3},"r":{"a":0,"k":0,"ix":6},"o":{"a":0,"k":100,"ix":7},"sk":{"a":0,"k":0,"ix":4},"sa":{"a":0,"k":0,"ix":5},"nm":"Transform"}],"nm":"Group 1","np":1,"cix":2,"bm":0,"ix":1,"mn":"ADBE Vector Group","hd":false},{"ty":"st","c":{"a":0,"k":[0,0,0,1],"ix":3,"x":"var $bm_rt;\n$bm_rt = thisComp.layer('Main Stroke width - Color Ctrl').effect('Base Color')('Color');"},"o":{"a":0,"k":100,"ix":4},"w":{"a":0,"k":16,"ix":5,"x":"var $bm_rt;\n$bm_rt = thisComp.layer('Main Stroke width - Color Ctrl').effect('Stroke width')('Slider');"},"lc":2,"lj":2,"bm":0,"nm":"Stroke 1","mn":"ADBE Vector Graphic - Stroke","hd":false},{"ty":"tr","p":{"a":0,"k":[0,44],"ix":2},"a":{"a":0,"k":[0,43],"ix":1},"s":{"a":0,"k":[100,100],"ix":3},"r":{"a":0,"k":0,"ix":6},"o":{"a":0,"k":100,"ix":7},"sk":{"a":0,"k":0,"ix":4},"sa":{"a":0,"k":0,"ix":5},"nm":"Transform"}],"nm":"Petal 01","np":2,"cix":2,"bm":0,"ix":1,"mn":"ADBE Vector Group","hd":false}],"ip":0,"op":180,"st":0,"bm":0},{"ddd":0,"ind":7,"ty":4,"nm":"01","parent":6,"sr":1,"ks":{"o":{"a":0,"k":100,"ix":11},"r":{"a":0,"k":0,"ix":10},"p":{"a":0,"k":[-0.049,17.597,0],"ix":2,"l":2},"a":{"a":0,"k":[250,192.919,0],"ix":1,"l":2},"s":{"a":0,"k":[100,100,100],"ix":6,"l":2}},"ao":0,"shapes":[{"ty":"gr","it":[{"ind":0,"ty":"sh","ix":1,"ks":{"a":1,"k":[{"i":{"x":0.667,"y":1},"o":{"x":0.333,"y":0},"t":15,"s":[{"i":[[13.237,6.62],[9.067,-16.637],[0,0],[11.98,6.927],[-4.547,9.814],[-6.653,-5.315],[-8.352,4.177],[-9.199,-4.6],[-7.063,-6.569],[-7.268,3.69],[-2.139,-10.48],[6.246,-12.57],[0,0]],"o":[[-13.207,6.605],[0,0],[-6.316,-12.422],[2.139,-10.479],[7.268,3.69],[7.063,-6.569],[9.199,-4.601],[8.353,4.177],[6.653,-5.315],[4.546,9.814],[-12.094,6.993],[0,0],[-9.068,-16.688]],"v":[[0,-2.692],[-35.618,34.316],[-37.316,32.618],[-68.665,2.351],[-58.458,-28.262],[-37.364,-14.593],[-14.147,-30.981],[14.146,-30.981],[37.364,-14.593],[58.458,-28.262],[68.665,2.351],[37.137,32.974],[35.68,34.431]],"c":true}]},{"i":{"x":0.667,"y":1},"o":{"x":0.333,"y":0},"t":81,"s":[{"i":[[13.237,6.62],[9.067,-16.637],[0,0],[11.98,6.927],[-4.547,9.814],[-6.653,-5.315],[-8.352,4.177],[-9.199,-4.6],[-7.063,-6.569],[-7.268,3.69],[-2.139,-10.48],[6.246,-12.57],[0,0]],"o":[[-13.207,6.605],[0,0],[-6.316,-12.422],[2.139,-10.479],[7.268,3.69],[7.063,-6.569],[9.199,-4.601],[8.353,4.177],[6.653,-5.315],[4.546,9.814],[-12.094,6.993],[0,0],[-9.068,-16.688]],"v":[[0,-2.692],[-35.618,34.316],[-37.316,32.618],[-70.54,0.726],[-58.083,-44.137],[-36.989,-30.468],[-13.772,-46.856],[14.521,-46.856],[37.739,-30.468],[58.833,-44.137],[68.665,2.351],[37.137,32.974],[35.68,34.431]],"c":true}]},{"t":153,"s":[{"i":[[13.237,6.62],[9.067,-16.637],[0,0],[11.98,6.927],[-4.547,9.814],[-6.653,-5.315],[-8.352,4.177],[-9.199,-4.6],[-7.063,-6.569],[-7.268,3.69],[-2.139,-10.48],[6.246,-12.57],[0,0]],"o":[[-13.207,6.605],[0,0],[-6.316,-12.422],[2.139,-10.479],[7.268,3.69],[7.063,-6.569],[9.199,-4.601],[8.353,4.177],[6.653,-5.315],[4.547,9.814],[-12.094,6.993],[0,0],[-9.068,-16.688]],"v":[[0,-2.692],[-35.618,34.316],[-37.316,32.618],[-68.665,2.351],[-58.458,-28.262],[-37.364,-14.593],[-14.147,-30.981],[14.146,-30.981],[37.364,-14.593],[58.458,-28.262],[68.665,2.351],[37.137,32.974],[35.68,34.431]],"c":true}]}],"ix":2},"nm":"Path 1","mn":"ADBE Vector Shape - Group","hd":false},{"ty":"fl","c":{"a":0,"k":[0.407843142748,0.392156869173,0.96862745285,1],"ix":4},"o":{"a":0,"k":100,"ix":5},"r":1,"bm":0,"nm":"Fill 1","mn":"ADBE Vector Graphic - Fill","hd":false},{"ty":"tr","p":{"a":0,"k":[250,222.374],"ix":2},"a":{"a":0,"k":[0,0],"ix":1},"s":{"a":0,"k":[100,100],"ix":3},"r":{"a":0,"k":0,"ix":6},"o":{"a":0,"k":100,"ix":7},"sk":{"a":0,"k":0,"ix":4},"sa":{"a":0,"k":0,"ix":5},"nm":"Transform"}],"nm":"shadow","np":2,"cix":2,"bm":0,"ix":1,"mn":"ADBE Vector Group","hd":false},{"ty":"gr","it":[{"ind":0,"ty":"sh","ix":1,"ks":{"a":0,"k":{"i":[[13.238,6.62],[9.067,-16.637],[0,0],[11.98,6.927],[-31.5,12.841],[-8.5,-41.644],[6.246,-12.57],[0,0]],"o":[[-13.207,6.605],[0,0],[-6.316,-12.423],[8.5,-41.644],[36.875,14.091],[-12.094,6.993],[0,0],[-9.068,-16.688]],"v":[[0,26.762],[-35.618,63.771],[-37.316,62.073],[-70.54,30.181],[0,-63.886],[68.665,31.806],[37.137,62.429],[35.68,63.886]],"c":true},"ix":2},"nm":"Path 1","mn":"ADBE Vector Shape - Group","hd":false},{"ty":"fl","c":{"a":0,"k":[0.737254917622,0.603921592236,0.956862747669,1],"ix":4},"o":{"a":0,"k":100,"ix":5},"r":1,"bm":0,"nm":"Fill 1","mn":"ADBE Vector Graphic - Fill","hd":false},{"ty":"tr","p":{"a":0,"k":[250,192.919],"ix":2},"a":{"a":0,"k":[0,0],"ix":1},"s":{"a":0,"k":[100,100],"ix":3},"r":{"a":0,"k":0,"ix":6},"o":{"a":0,"k":100,"ix":7},"sk":{"a":0,"k":0,"ix":4},"sa":{"a":0,"k":0,"ix":5},"nm":"Transform"}],"nm":"Group 2","np":2,"cix":2,"bm":0,"ix":2,"mn":"ADBE Vector Group","hd":false}],"ip":0,"op":180,"st":0,"bm":0},{"ddd":0,"ind":8,"ty":4,"nm":"Leaves 01","sr":1,"ks":{"o":{"a":0,"k":100,"ix":11},"r":{"a":0,"k":0,"ix":10},"p":{"a":0,"k":[250,376.785,0],"ix":2,"l":2},"a":{"a":0,"k":[0,0,0],"ix":1,"l":2},"s":{"a":0,"k":[100,100,100],"ix":6,"l":2}},"ao":0,"shapes":[{"ty":"gr","it":[{"ind":0,"ty":"sh","ix":1,"ks":{"a":0,"k":{"i":[[0,0],[0,0]],"o":[[0,0],[0,0]],"v":[[0,11.637],[0,-11.637]],"c":false},"ix":2},"nm":"Path 1","mn":"ADBE Vector Shape - Group","hd":false},{"ty":"st","c":{"a":0,"k":[0.568627476692,0.717647075653,0.023529414088,1],"ix":3},"o":{"a":0,"k":100,"ix":4},"w":{"a":0,"k":16,"ix":5,"x":"var $bm_rt;\n$bm_rt = thisComp.layer('Main Stroke width - Color Ctrl').effect('Stroke width')('Slider');"},"lc":2,"lj":2,"bm":0,"nm":"Stroke 1","mn":"ADBE Vector Graphic - Stroke","hd":false},{"ty":"tr","p":{"a":0,"k":[0,-6.5],"ix":2},"a":{"a":0,"k":[0,0],"ix":1},"s":{"a":0,"k":[100,100],"ix":3},"r":{"a":0,"k":0,"ix":6},"o":{"a":0,"k":100,"ix":7},"sk":{"a":0,"k":0,"ix":4},"sa":{"a":0,"k":0,"ix":5},"nm":"Transform"}],"nm":"Line","np":2,"cix":2,"bm":0,"ix":1,"mn":"ADBE Vector Group","hd":false},{"ty":"gr","it":[{"ind":0,"ty":"sh","ix":1,"ks":{"a":1,"k":[{"i":{"x":0.667,"y":1},"o":{"x":0.333,"y":0},"t":16,"s":[{"i":[[0,0],[0,0],[-24.529,13.591]],"o":[[-19.165,50.411],[0,-22.404],[0,0]],"v":[[-76.062,-32.848],[-154,9.913],[-117.4,-45.123]],"c":false}]},{"i":{"x":0.667,"y":1},"o":{"x":0.167,"y":0},"t":80,"s":[{"i":[[0,0],[0,0],[-24.529,13.591]],"o":[[-19.438,52.063],[0,-22.404],[0,0]],"v":[[-79.812,-23.598],[-165.5,16.913],[-130.15,-36.373]],"c":false}]},{"t":152,"s":[{"i":[[0,0],[0,0],[-24.529,13.591]],"o":[[-19.165,50.411],[0,-22.404],[0,0]],"v":[[-76.062,-32.848],[-154,9.913],[-117.4,-45.123]],"c":false}]}],"ix":2},"nm":"Path 1","mn":"ADBE Vector Shape - Group","hd":false},{"ind":1,"ty":"sh","ix":2,"ks":{"a":1,"k":[{"i":{"x":0.667,"y":1},"o":{"x":0.333,"y":0},"t":16,"s":[{"i":[[0,0],[0,-22.516],[19.272,50.115]],"o":[[24.776,13.604],[0,0],[0,0]],"v":[[117.033,-45.325],[154,9.913],[76.164,-32.58]],"c":false}]},{"i":{"x":0.667,"y":1},"o":{"x":0.167,"y":0},"t":80,"s":[{"i":[[0,0],[0,-22.516],[21.086,60.295]],"o":[[24.776,13.604],[0,0],[0,0]],"v":[[125.533,-34.575],[160.5,19.163],[72.414,-23.33]],"c":false}]},{"t":152,"s":[{"i":[[0,0],[0,-22.516],[19.272,50.115]],"o":[[24.776,13.604],[0,0],[0,0]],"v":[[117.033,-45.325],[154,9.913],[76.164,-32.58]],"c":false}]}],"ix":2},"nm":"Path 2","mn":"ADBE Vector Shape - Group","hd":false},{"ind":2,"ty":"sh","ix":3,"ks":{"a":1,"k":[{"i":{"x":0.667,"y":1},"o":{"x":0.333,"y":0},"t":16,"s":[{"i":[[0,0],[21.751,-10.877],[-2.17,30.396]],"o":[[2.07,30.345],[-21.794,-10.898],[0,0]],"v":[[41.845,-28.497],[0,45.325],[-41.833,-28.676]],"c":false}]},{"i":{"x":0.667,"y":1},"o":{"x":0.167,"y":0},"t":80,"s":[{"i":[[0,0],[21.751,-10.877],[-2.17,30.396]],"o":[[2.07,30.345],[-21.794,-10.898],[0,0]],"v":[[42.845,-19.747],[-2.75,65.825],[-50.833,-19.176]],"c":false}]},{"t":152,"s":[{"i":[[0,0],[21.751,-10.877],[-2.17,30.396]],"o":[[2.07,30.345],[-21.794,-10.898],[0,0]],"v":[[41.845,-28.497],[0,45.325],[-41.833,-28.676]],"c":false}]}],"ix":2},"nm":"Path 3","mn":"ADBE Vector Shape - Group","hd":false},{"ty":"st","c":{"a":0,"k":[0.20000000298,0.800000011921,0.800000011921,1],"ix":3,"x":"var $bm_rt;\n$bm_rt = thisComp.layer('Main Stroke width - Color Ctrl').effect('Base Color')('Color');"},"o":{"a":0,"k":100,"ix":4},"w":{"a":0,"k":16,"ix":5,"x":"var $bm_rt;\n$bm_rt = thisComp.layer('Main Stroke width - Color Ctrl').effect('Stroke width')('Slider');"},"lc":2,"lj":2,"bm":0,"nm":"Stroke 1","mn":"ADBE Vector Graphic - Stroke","hd":false},{"ty":"fl","c":{"a":0,"k":[0.694117647059,0.850980392157,0.321568627451,1],"ix":4},"o":{"a":0,"k":100,"ix":5},"r":1,"bm":0,"nm":"Fill 1","mn":"ADBE Vector Graphic - Fill","hd":false},{"ty":"tr","p":{"a":0,"k":[0,0],"ix":2},"a":{"a":0,"k":[0,0],"ix":1},"s":{"a":0,"k":[100,100],"ix":3},"r":{"a":0,"k":0,"ix":6},"o":{"a":0,"k":100,"ix":7},"sk":{"a":0,"k":0,"ix":4},"sa":{"a":0,"k":0,"ix":5},"nm":"Transform"}],"nm":"Leaves 01","np":5,"cix":2,"bm":0,"ix":2,"mn":"ADBE Vector Group","hd":false}],"ip":0,"op":180,"st":0,"bm":0},{"ddd":0,"ind":9,"ty":4,"nm":"Leaves 02","sr":1,"ks":{"o":{"a":0,"k":100,"ix":11},"r":{"a":0,"k":0,"ix":10},"p":{"a":0,"k":[251.352,382.25,0],"ix":2,"l":2},"a":{"a":0,"k":[0,0,0],"ix":1,"l":2},"s":{"a":0,"k":[100,100,100],"ix":6,"l":2}},"ao":0,"shapes":[{"ty":"gr","it":[{"ind":0,"ty":"sh","ix":1,"ks":{"a":1,"k":[{"i":{"x":0.667,"y":1},"o":{"x":0.333,"y":0},"t":16,"s":[{"i":[[0,0],[-0.071,-0.729],[-11.994,-9.138],[-9.253,16.747],[-0.208,0.408]],"o":[[0.051,0.739],[1.905,19.463],[11.356,-2.31],[0.223,-0.405],[0,0]],"v":[[-101.352,-37.25],[-101.639,-5.25],[-78.586,39.25],[-35.371,6.75],[-14.352,-25.25]],"c":false}]},{"i":{"x":0.667,"y":1},"o":{"x":0.333,"y":0},"t":80,"s":[{"i":[[0,0],[-0.071,-0.729],[-18.016,-12.75],[-9.253,16.747],[-0.208,0.408]],"o":[[0.051,0.739],[1.905,19.463],[18.484,-2.75],[0.223,-0.405],[0,0]],"v":[[-107.352,-37.25],[-107.639,-5.25],[-81.336,47],[-31.621,8.5],[-10.602,-23.5]],"c":false}]},{"t":152,"s":[{"i":[[0,0],[-0.071,-0.729],[-11.994,-9.138],[-9.253,16.747],[-0.208,0.408]],"o":[[0.051,0.739],[1.905,19.463],[11.356,-2.31],[0.223,-0.405],[0,0]],"v":[[-101.352,-37.25],[-101.639,-5.25],[-78.586,39.25],[-35.371,6.75],[-14.352,-25.25]],"c":false}]}],"ix":2},"nm":"Path 1","mn":"ADBE Vector Shape - Group","hd":false},{"ind":1,"ty":"sh","ix":2,"ks":{"a":1,"k":[{"i":{"x":0.667,"y":1},"o":{"x":0.333,"y":0},"t":16,"s":[{"i":[[0,0],[0.078,-0.799],[11.994,-9.138],[9.253,16.747],[0.256,0.515]],"o":[[-0.053,0.811],[-1.905,19.463],[-11.356,-2.31],[-0.281,-0.509],[0,0]],"v":[[101.648,-39.25],[98.935,-5.25],[75.881,39.25],[32.666,6.75],[16.648,-24.25]],"c":false}]},{"i":{"x":0.667,"y":1},"o":{"x":0.333,"y":0},"t":80,"s":[{"i":[[0,0],[0.078,-0.799],[16.016,-10.5],[11.481,31.25],[0.256,0.515]],"o":[[-0.053,0.811],[-1.905,19.463],[-18.984,-3.75],[-0.201,-0.546],[0,0]],"v":[[106.898,-39.25],[104.185,-4.25],[80.631,52.5],[28.166,5.5],[16.648,-24.25]],"c":false}]},{"t":152,"s":[{"i":[[0,0],[0.078,-0.799],[11.994,-9.138],[9.253,16.747],[0.256,0.515]],"o":[[-0.053,0.811],[-1.905,19.463],[-11.356,-2.31],[-0.281,-0.509],[0,0]],"v":[[101.648,-39.25],[98.935,-5.25],[75.881,39.25],[32.666,6.75],[16.648,-24.25]],"c":false}]}],"ix":2},"nm":"Path 2","mn":"ADBE Vector Shape - Group","hd":false},{"ty":"st","c":{"a":0,"k":[0.20000000298,0.800000011921,0.800000011921,1],"ix":3,"x":"var $bm_rt;\n$bm_rt = thisComp.layer('Main Stroke width - Color Ctrl').effect('Base Color')('Color');"},"o":{"a":0,"k":100,"ix":4},"w":{"a":0,"k":16,"ix":5,"x":"var $bm_rt;\n$bm_rt = thisComp.layer('Main Stroke width - Color Ctrl').effect('Stroke width')('Slider');"},"lc":2,"lj":2,"bm":0,"nm":"Stroke 1","mn":"ADBE Vector Graphic - Stroke","hd":false},{"ty":"tr","p":{"a":0,"k":[0,0],"ix":2},"a":{"a":0,"k":[0,0],"ix":1},"s":{"a":0,"k":[100,100],"ix":3},"r":{"a":0,"k":0,"ix":6},"o":{"a":0,"k":100,"ix":7},"sk":{"a":0,"k":0,"ix":4},"sa":{"a":0,"k":0,"ix":5},"nm":"Transform"}],"nm":"Leaves 02","np":3,"cix":2,"bm":0,"ix":1,"mn":"ADBE Vector Group","hd":false},{"ty":"fl","c":{"a":0,"k":[0.56862745098,0.717647058824,0.023529411765,1],"ix":4},"o":{"a":0,"k":100,"ix":5},"r":1,"bm":0,"nm":"Fill 1","mn":"ADBE Vector Graphic - Fill","hd":false}],"ip":0,"op":180,"st":0,"bm":0}],"markers":[{"tm":15,"cm":"1","dr":0},{"tm":44,"cm":"2","dr":0},{"tm":81,"cm":"3","dr":0},{"tm":152,"cm":"4","dr":0},{"tm":166,"cm":"FIN\r\n","dr":0}]}